homevolt/__init__.py
homevolt/const.py
homevolt/device.py
homevolt/exceptions.py
homevolt/homevolt.py
homevolt/models.py
homevolt-0.2.4.dist-info/METADATA
homevolt-0.2.4.dist-info/WHEEL
homevolt-0.2.4.dist-info/top_level.txt
homevolt-0.2.4.dist-info/RECORD
