Metadata-Version: 2.4
Name: Homevolt
Version: 0.2.4
Summary: Python library for Homevolt EMS devices
Author-email: Your Name <your.email@example.com>
License: GPL-3.0
Classifier: Development Status :: 4 - Beta
Classifier: Intended Audience :: Developers
Classifier: License :: OSI Approved :: GNU General Public License v3 (GPLv3)
Classifier: Programming Language :: Python :: 3
Classifier: Programming Language :: Python :: 3.12
Classifier: Programming Language :: Python :: 3.13
Requires-Python: >=3.12
Requires-Dist: aiohttp>=3.8.0
